promptutils/__init__.py
promptutils-0.1.0.dist-info/METADATA
promptutils-0.1.0.dist-info/WHEEL
promptutils-0.1.0.dist-info/top_level.txt
promptutils-0.1.0.dist-info/RECORD
