Metadata-Version: 2.4
Name: promptutils
Version: 0.1.0
Summary: Utilities for working with LLM prompts
Author-email: testycool <left@testy.cool>
License: MIT
Project-URL: Homepage, https://github.com/testy-cool/promptutils
Project-URL: Repository, https://github.com/testy-cool/promptutils
Requires-Python: >=3.8
